easy_bigquery/__init__.py
easy_bigquery/connector/__init__.py
easy_bigquery/connector/connector.py
easy_bigquery/context/__init__.py
easy_bigquery/context/manager.py
easy_bigquery/core/__init__.py
easy_bigquery/core/config.py
easy_bigquery/logger/__init__.py
easy_bigquery/logger/manager.py
easy_bigquery/workers/__init__.py
easy_bigquery/workers/fetch.py
easy_bigquery/workers/push.py
easy_bigquery-0.1.1a0.dist-info/LICENSE.txt
easy_bigquery-0.1.1a0.dist-info/METADATA
easy_bigquery-0.1.1a0.dist-info/WHEEL
easy_bigquery-0.1.1a0.dist-info/RECORD
