Metadata-Version: 2.3
Name: easy-bigquery
Version: 0.1.1a0
Summary: Easy BigQuery is a Python package designed to simplify interactions with Google BigQuery. It provides a high-level API for connecting, fetching, and pushing data, allowing you to focus on your data analysis instead of boilerplate code.
License: MIT
Author: AndreAmorim05
Author-email: js.andreamorim@gmail.com
Requires-Python: >=3.13,<4.0
Classifier: License :: OSI Approved :: MIT License
Classifier: Programming Language :: Python :: 3
Classifier: Programming Language :: Python :: 3.13
Requires-Dist: db-dtypes (>=1.4.2,<2.0.0)
Requires-Dist: google-cloud-bigquery (>=3.31.0,<4.0.0)
Requires-Dist: google-cloud-bigquery-storage (>=2.31.0,<3.0.0)
Requires-Dist: loguru (>=0.7.3,<0.8.0)
Requires-Dist: pandas (>=2.3.0,<3.0.0)
Requires-Dist: pandas-gbq (>=0.29.0,<0.30.0)
Requires-Dist: python-decouple (>=3.8,<4.0)
Project-URL: Bug Tracker, https://github.com/AndreAmorim05/easy-bigquery/issues
Project-URL: Documentation, https://easy-bigquery.readthedocs.io/en/latest/
Project-URL: Home Page, https://easy-bigquery.readthedocs.io/en/latest/
Project-URL: Source Code, https://github.com/AndreAmorim05/easy-bigquery
